zippy_form/__init__.py
zippy_form/celery.py
zippy_form/celery_tasks.py
zippy_form/event_test.py
zippy_form/event_webhook_triggers.py
zippy_form/gsheet.py
zippy_form/models.py
zippy_form/permissions.py
zippy_form/serializers.py
zippy_form/timezone.py
zippy_form/urls.py
zippy_form/utils.py
zippy_form/validation_rule.py
zippy_form/validation_rule_schema.py
zippy_form/views.py
zippy_form/management/commands/celery_init.py
zippy_form/management/commands/__pycache__/celery_init.cpython-38.pyc
zippy_form/migrations/0001_initial.py
zippy_form/migrations/0002_account_meta_detail_form_meta_detail.py
zippy_form/migrations/0003_formsubmission_entry.py
zippy_form/migrations/0004_rename_entry_formsubmission_revision.py
zippy_form/migrations/0005_account_admin_email.py
zippy_form/migrations/0006_form_gsheet_url.py
zippy_form/migrations/0007_formsubmissiondata_submission_reference.py
zippy_form/migrations/0008_webhook.py
zippy_form/migrations/0009_alter_webhook_endpoint_url.py
zippy_form/migrations/0010_account_timezone_formsubmission_api_accessed_count.py
zippy_form/migrations/0011_remove_form_created_by_and_more.py
zippy_form/migrations/0012_paymentgatewaywebhook_formfield_slug_and_more.py
zippy_form/migrations/0013_formsubmissionpaymentdetails.py
zippy_form/migrations/0014_remove_account_stripe_connect_redirect_url.py
zippy_form/migrations/0015_form_category_form_qrcode_alter_formfield_field_type.py
zippy_form/migrations/0016_formsubmissionpaymentdetails_payment_mode_and_more.py
zippy_form/migrations/0017_formsubmissionpaymentdetails_currency_and_more.py
zippy_form/migrations/0018_remove_formsubmissionpaymentdetails_payment_gateway_status_and_more.py
zippy_form/migrations/0019_formmetadata_formmetadataoption_and_more.py
zippy_form/migrations/0020_formrecaptcha_formpageviews.py
zippy_form/migrations/0021_formfield_admin_only.py
zippy_form/migrations/0022_form_non_admin_qrcode.py
zippy_form/migrations/0023_formsubmission_submission_owner_and_more.py
zippyform-1.4.82.dist-info/METADATA
zippyform-1.4.82.dist-info/WHEEL
zippyform-1.4.82.dist-info/top_level.txt
zippyform-1.4.82.dist-info/RECORD
