Metadata-Version: 2.1
Name: zippyform
Version: 1.4.82
Summary: Streamline form development in Django effortlessly with this quick and code-free package. Create dynamic forms without writing code, making form development a breeze.
Home-page: UNKNOWN
Author: Karthick Sivakumar
Author-email: karthik@zaigoinfotech.com
License: UNKNOWN
Platform: UNKNOWN
Requires-Dist: Django>=3.0.0
Requires-Dist: celery>=5.3.4
Requires-Dist: chardet==5.2.0
Requires-Dist: djangorestframework>=3.0.0
Requires-Dist: google-api-python-client>=2.137.0
Requires-Dist: google-auth-httplib2>=0.2.0
Requires-Dist: google-auth-oauthlib>=1.1.0
Requires-Dist: gspread>=5.11.3
Requires-Dist: jsonschema>=4.17.3
Requires-Dist: oauth2client>=4.1.3
Requires-Dist: openpyxl==3.1.2
Requires-Dist: pandas==2.0.3
Requires-Dist: qrcode>=7.4.2
Requires-Dist: stripe>=7.5.0
